pywmm/__init__.py
pywmm/calculator.py
pywmm/coefficient_handler.py
pywmm/coefficients.py
pywmm/core.py
pywmm/date_utils.py
pywmm/data/WMM.COF
pywmm-1.1.1.dist-info/licenses/LICENSE
pywmm-1.1.1.dist-info/METADATA
pywmm-1.1.1.dist-info/WHEEL
pywmm-1.1.1.dist-info/top_level.txt
pywmm-1.1.1.dist-info/RECORD
