Metadata-Version: 2.4
Name: pywmm
Version: 1.1.1
Summary: World Magnetic Model (WMM) calculations in Python
Home-page: https://github.com/dougcr95/pywmm
Author: Douglas Rojas
Author-email: dougcr95@gmail.com
Project-URL: Bug Reports, https://github.com/dougc95/pywmm/issues
Project-URL: Source, https://github.com/dougc95/pywmm
Project-URL: Documentation, https://github.com/dougc95/pywmm/blob/main/README.md
Keywords: geomagnetic field navigation compass declination inclination WMM
Classifier: Development Status :: 4 - Beta
Classifier: Intended Audience :: Science/Research
Classifier: Intended Audience :: Developers
Classifier: License :: OSI Approved :: MIT License
Classifier: Programming Language :: Python :: 3
Classifier: Programming Language :: Python :: 3.6
Classifier: Programming Language :: Python :: 3.7
Classifier: Programming Language :: Python :: 3.8
Classifier: Programming Language :: Python :: 3.9
Classifier: Programming Language :: Python :: 3.10
Classifier: Programming Language :: Python :: 3.11
Classifier: Topic :: Scientific/Engineering :: Physics
Classifier: Topic :: Scientific/Engineering :: GIS
Classifier: Operating System :: OS Independent
Requires-Python: >=3.6
License-File: LICENSE
Requires-Dist: numpy
Dynamic: author
Dynamic: author-email
Dynamic: classifier
Dynamic: description
Dynamic: description-content-type
Dynamic: home-page
Dynamic: keywords
Dynamic: license-file
Dynamic: project-url
Dynamic: requires-dist
Dynamic: requires-python
Dynamic: summary
